finalflash/__init__.py
finalflash/beam_corrector.py
finalflash/bp.py
finalflash-0.3.6.dist-info/LICENSE
finalflash-0.3.6.dist-info/METADATA
finalflash-0.3.6.dist-info/WHEEL
finalflash-0.3.6.dist-info/entry_points.txt
finalflash-0.3.6.dist-info/top_level.txt
finalflash-0.3.6.dist-info/RECORD
