Metadata-Version: 2.1
Name: finalflash
Version: 0.3.6
Summary: A tool for uGMRT primary beam correction
Home-page: https://github.com/arpan-52/Finalflash
Author: Arpan Pal
Author-email: arpan522000@gmail.com
Classifier: Programming Language :: Python :: 3
Classifier: License :: OSI Approved :: MIT License
Classifier: Operating System :: OS Independent
Requires-Python: >=3.6
License-File: LICENSE
Requires-Dist: numpy
Requires-Dist: astropy
